README.rst
setup.py
collective/__init__.py
collective.js.contentflow.egg-info/PKG-INFO
collective.js.contentflow.egg-info/SOURCES.txt
collective.js.contentflow.egg-info/dependency_links.txt
collective.js.contentflow.egg-info/entry_points.txt
collective.js.contentflow.egg-info/namespace_packages.txt
collective.js.contentflow.egg-info/not-zip-safe
collective.js.contentflow.egg-info/requires.txt
collective.js.contentflow.egg-info/top_level.txt
collective/js/__init__.py
collective/js/contentflow/__init__.py
collective/js/contentflow/configure.zcml
collective/js/contentflow/tests.py
collective/js/contentflow/static/ContentFlowAddOn_black.css
collective/js/contentflow/static/ContentFlowAddOn_black.js
collective/js/contentflow/static/ContentFlowAddOn_gallery.js
collective/js/contentflow/static/ContentFlowAddOn_lightbox.js
collective/js/contentflow/static/ContentFlowAddOn_roundabout.js
collective/js/contentflow/static/ContentFlowAddOn_screwdriver.js
collective/js/contentflow/static/ContentFlowAddOn_slideshow.css
collective/js/contentflow/static/ContentFlowAddOn_slideshow.js
collective/js/contentflow/static/ContentFlowAddOn_white.css
collective/js/contentflow/static/ContentFlowAddOn_white.js
collective/js/contentflow/static/contentflow.css
collective/js/contentflow/static/contentflow.js
collective/js/contentflow/static/contentflow_src.css
collective/js/contentflow/static/contentflow_src.js
collective/js/contentflow/static/styles.css
collective/js/contentflow/static/title.png
collective/js/contentflow/static/img/.blank.gif.swp
collective/js/contentflow/static/img/1x1_0.5_black.png
collective/js/contentflow/static/img/1x1_0.5_white.png
collective/js/contentflow/static/img/blank.gif
collective/js/contentflow/static/img/icons.svg
collective/js/contentflow/static/img/loader.gif
collective/js/contentflow/static/img/loader_black.gif
collective/js/contentflow/static/img/loader_white.gif
collective/js/contentflow/static/img/scrollbar_black.png
collective/js/contentflow/static/img/scrollbar_white.png
collective/js/contentflow/static/img/slider_black.png
collective/js/contentflow/static/img/slider_white.png
collective/js/contentflow/static/img/slideshow_button.gif
collective/js/contentflow/static/img/slideshow_button.png
collective/js/contentflow/static/img/slideshow_ff.gif
collective/js/contentflow/static/img/slideshow_ff.png
