Metadata-Version: 1.0
Name: collective.js.contentflow
Version: 1.0
Summary: contentflow js integration for plone
Home-page: https://github.com/collective/collective.js.contentflow
Author: Nathan Van Gheem
Author-email: vangheem@gmail.com
License: GPL
Keywords: plone contentflow js
Platform: UNKNOWN
Classifier: Framework :: Plone
Classifier: Programming Language :: Python
